<?xml version='1.0' encoding='utf-8'?><!-- Камни Стихии -->
<list xmlns:xsi="http://www.w3.org/2001/XMLSchema-instance" xsi:noNamespaceSchemaLocation="../xsd/multisell.xsd">
<item><ingredient id="6673" count="7"/><production id="9546" count="1"/></item><!-- Fire Stone -->
<item><ingredient id="6673" count="7"/><production id="9547" count="1"/></item><!-- Water Stone -->
<item><ingredient id="6673" count="7"/><production id="9548" count="1"/></item><!-- Earth Stone -->
<item><ingredient id="6673" count="7"/><production id="9549" count="1"/></item><!-- Wind Stone -->
<item><ingredient id="6673" count="7"/><production id="9550" count="1"/></item><!-- Dark Stone -->
<item><ingredient id="6673" count="7"/><production id="9551" count="1"/></item><!-- Divine Stone -->
<item><ingredient id="9546" count="1"/><ingredient id="6673" count="15"/><production id="9552" count="1"/></item><!-- Fire Crystal -->
<item><ingredient id="9547" count="1"/><ingredient id="6673" count="15"/><production id="9553" count="1"/></item><!-- Water Crystal -->
<item><ingredient id="9548" count="1"/><ingredient id="6673" count="15"/><production id="9554" count="1"/></item><!-- Earth Crystal -->
<item><ingredient id="9549" count="1"/><ingredient id="6673" count="15"/><production id="9555" count="1"/></item><!-- Wind Crystal -->
<item><ingredient id="9550" count="1"/><ingredient id="6673" count="15"/><production id="9556" count="1"/></item><!-- Dark Crystal -->
<item><ingredient id="9551" count="1"/><ingredient id="6673" count="15"/><production id="9557" count="1"/></item><!-- Divine Crystal -->
<item><ingredient id="9552" count="1"/><ingredient id="6673" count="20"/><production id="9558" count="1"/></item><!-- Fire Jewel -->
<item><ingredient id="9553" count="1"/><ingredient id="6673" count="20"/><production id="9559" count="1"/></item><!-- Water Jewel -->
<item><ingredient id="9554" count="1"/><ingredient id="6673" count="20"/><production id="9560" count="1"/></item><!-- Earth Jewel -->
<item><ingredient id="9555" count="1"/><ingredient id="6673" count="20"/><production id="9561" count="1"/></item><!-- Wind Jewel -->
<item><ingredient id="9556" count="1"/><ingredient id="6673" count="20"/><production id="9562" count="1"/></item><!-- Dark Jewel -->
<item><ingredient id="9557" count="1"/><ingredient id="6673" count="20"/><production id="9563" count="1"/></item><!-- Divine Jewel -->
<item><ingredient id="9558" count="1"/><ingredient id="6673" count="30"/><production id="9564" count="1"/></item><!-- Fire Energy -->
<item><ingredient id="9559" count="1"/><ingredient id="6673" count="30"/><production id="9565" count="1"/></item><!-- Water Energy -->
<item><ingredient id="9560" count="1"/><ingredient id="6673" count="30"/><production id="9566" count="1"/></item><!-- Earth Energy -->
<item><ingredient id="9561" count="1"/><ingredient id="6673" count="30"/><production id="9567" count="1"/></item><!-- Wind Energy -->
<item><ingredient id="9562" count="1"/><ingredient id="6673" count="30"/><production id="9568" count="1"/></item><!-- Dark Energy -->
<item><ingredient id="9563" count="1"/><ingredient id="6673" count="30"/><production id="9569" count="1"/></item><!-- Divine Energy -->
</list>